{
 "name": "The Title Page of a Detective Novel Torn Off by Luocha",
 "iconPath": "a3dcdeaef3a7d460de1b86b57c802fe293c53246d3b55b49d94ae502d9f3d275",
 "desc": "None",
 "volumes": [
  {
   "title": "The Title Page of a Detective Novel Torn Off by Luocha",
   "localTitle": "The Title Page of a Detective Novel Torn Off by Luocha",
   "localDesc": "To the next reader:<br />The killer is Chang Hong, the nephew of Chang the Ninth.<br />Yours sincerely<br />Best regards<br /><align=\"right\">The Immortal Spoiler</align>",
   "images": []
  }
 ],
 "pageId": "209340"
}